odoo/addons/shopinvader_sale_cart/README.rst
odoo/addons/shopinvader_sale_cart/__init__.py
odoo/addons/shopinvader_sale_cart/__manifest__.py
odoo/addons/shopinvader_sale_cart/i18n/shopinvader_sale_cart.pot
odoo/addons/shopinvader_sale_cart/models/__init__.py
odoo/addons/shopinvader_sale_cart/models/sale_order.py
odoo/addons/shopinvader_sale_cart/models/sale_order_line.py
odoo/addons/shopinvader_sale_cart/readme/CONTRIBUTORS.rst
odoo/addons/shopinvader_sale_cart/readme/DESCRIPTION.rst
odoo/addons/shopinvader_sale_cart/static/description/icon.png
odoo/addons/shopinvader_sale_cart/static/description/index.html
odoo/addons/shopinvader_sale_cart/tests/__init__.py
odoo/addons/shopinvader_sale_cart/tests/test_sale_cart.py
odoo/addons/shopinvader_sale_cart/views/sale_order.xml
odoo_addon_shopinvader_sale_cart-16.0.1.2.0.dist-info/METADATA
odoo_addon_shopinvader_sale_cart-16.0.1.2.0.dist-info/WHEEL
odoo_addon_shopinvader_sale_cart-16.0.1.2.0.dist-info/top_level.txt
odoo_addon_shopinvader_sale_cart-16.0.1.2.0.dist-info/RECORD
