Metadata-Version: 2.1
Name: odoo-addon-shopinvader_sale_cart
Version: 16.0.1.2.0
Summary: ShopInvader logic for sale carts.
Home-page: https://github.com/shopinvader/odoo-shopinvader
Author: ACSONE SA/NV,Odoo Community Association (OCA)
Author-email: support@odoo-community.org
License: AGPL-3
Classifier: Programming Language :: Python
Classifier: Framework :: Odoo
Classifier: Framework :: Odoo :: 16.0
Classifier: License :: OSI Approved :: GNU Affero General Public License v3
Requires-Python: >=3.10
Requires-Dist: odoo-addon-onchange-helper<16.1dev,>=16.0dev
Requires-Dist: odoo-addon-sale-cart<16.1dev,>=16.0dev
Requires-Dist: odoo<16.1dev,>=16.0a
